sample/__init__.py
dfmodule_test-0.0.2.dist-info/METADATA
dfmodule_test-0.0.2.dist-info/WHEEL
dfmodule_test-0.0.2.dist-info/top_level.txt
dfmodule_test-0.0.2.dist-info/RECORD
